python/__init__.py
python/3/__init__.py
python/3/ida_allins.py
python/3/ida_auto.py
python/3/ida_bitrange.py
python/3/ida_bytes.py
python/3/ida_dbg.py
python/3/ida_dirtree.py
python/3/ida_diskio.py
python/3/ida_entry.py
python/3/ida_enum.py
python/3/ida_expr.py
python/3/ida_fixup.py
python/3/ida_fpro.py
python/3/ida_frame.py
python/3/ida_funcs.py
python/3/ida_gdl.py
python/3/ida_graph.py
python/3/ida_hexrays.py
python/3/ida_ida.py
python/3/ida_idaapi.py
python/3/ida_idc.py
python/3/ida_idd.py
python/3/ida_idp.py
python/3/ida_ieee.py
python/3/ida_kernwin.py
python/3/ida_lines.py
python/3/ida_loader.py
python/3/ida_moves.py
python/3/ida_nalt.py
python/3/ida_name.py
python/3/ida_netnode.py
python/3/ida_offset.py
python/3/ida_pro.py
python/3/ida_problems.py
python/3/ida_range.py
python/3/ida_registry.py
python/3/ida_search.py
python/3/ida_segment.py
python/3/ida_segregs.py
python/3/ida_srclang.py
python/3/ida_strlist.py
python/3/ida_struct.py
python/3/ida_tryblks.py
python/3/ida_typeinf.py
python/3/ida_ua.py
python/3/ida_xref.py
python/3/idaapi.py
python/3/idadex.py
python/3/idautils.py
python/3/idc.py
python/3/init.py
python/3/PyQt5/__init__.py
python/3/PyQt5/uic/__init__.py
python/3/PyQt5/uic/driver.py
python/3/PyQt5/uic/exceptions.py
python/3/PyQt5/uic/icon_cache.py
python/3/PyQt5/uic/objcreator.py
python/3/PyQt5/uic/properties.py
python/3/PyQt5/uic/pyuic.py
python/3/PyQt5/uic/uiparser.py
python/3/PyQt5/uic/Compiler/__init__.py
python/3/PyQt5/uic/Compiler/compiler.py
python/3/PyQt5/uic/Compiler/indenter.py
python/3/PyQt5/uic/Compiler/misc.py
python/3/PyQt5/uic/Compiler/proxy_metaclass.py
python/3/PyQt5/uic/Compiler/qobjectcreator.py
python/3/PyQt5/uic/Compiler/qtproxies.py
python/3/PyQt5/uic/Loader/__init__.py
python/3/PyQt5/uic/Loader/loader.py
python/3/PyQt5/uic/Loader/qobjectcreator.py
python/3/PyQt5/uic/port_v2/__init__.py
python/3/PyQt5/uic/port_v2/as_string.py
python/3/PyQt5/uic/port_v2/ascii_upper.py
python/3/PyQt5/uic/port_v2/proxy_base.py
YaraForge-0.1.16b1.dist-info/LICENSE
YaraForge-0.1.16b1.dist-info/METADATA
YaraForge-0.1.16b1.dist-info/WHEEL
YaraForge-0.1.16b1.dist-info/top_level.txt
YaraForge-0.1.16b1.dist-info/RECORD
